README
setup.py
xflash/XConfig.py
xflash/XFlash.py
xflash/XStatus.py
xflash/__init__.py
xflash.egg-info/PKG-INFO
xflash.egg-info/SOURCES.txt
xflash.egg-info/dependency_links.txt
xflash.egg-info/entry_points.txt
xflash.egg-info/not-zip-safe
xflash.egg-info/requires.txt
xflash.egg-info/top_level.txt