Metadata-Version: 1.0
Name: xflash
Version: 1.3.1
Summary: Xbox360 USB SPI Flasher client
Home-page: https://github.com/Juvenal1228/XFlash/
Author: Juvenal
Author-email: none@of.your.biz
License: BSD
Platform: UNKNOWN
